main.py
abllib/__init__.py
abllib/general.py
abllib/log.py
abllib/onexit.py
abllib/_storage/__init__.py
abllib/_storage/_base_storage.py
abllib/_storage/_internal_storage.py
abllib/alg/__init__.py
abllib/alg/_levenshtein.py
abllib/error/__init__.py
abllib/error/_custom_exception.py
abllib/error/_general.py
abllib/fs/__init__.py
abllib/fs/filename.py
abllib/fs/path.py
abllib/fuzzy/__init__.py
abllib/fuzzy/_all.py
abllib/fuzzy/_closest.py
abllib/fuzzy/_matchresult.py
abllib/fuzzy/_similarity.py
abllib/pproc/__init__.py
abllib/pproc/_worker_process.py
abllib/pproc/_worker_thread.py
abllib/storage/__init__.py
abllib/storage/_cache_storage.py
abllib/storage/_persistent_storage.py
abllib/storage/_storage_view.py
abllib/storage/_threadsafe_storage.py
abllib/storage/_volatile_storage.py
abllib/wrapper/__init__.py
abllib/wrapper/_base_log_wrapper.py
abllib/wrapper/_deprecated.py
abllib/wrapper/_lock.py
abllib/wrapper/_lock_wrapper.py
abllib/wrapper/_log_error.py
abllib/wrapper/_log_io.py
abllib/wrapper/_singleuse_wrapper.py
abllib/wrapper/_timeit.py
abllib-1.4.3.dist-info/licenses/LICENSE
test/__init__.py
test/alg_test.py
test/conftest.py
test/error_test.py
test/fixtures.py
test/fs_test.py
test/fuzzy_test.py
test/general_test.py
test/i_storage_test.py
test/log_test.py
test/mypy_test.py
test/onexit_test.py
test/pproc_test.py
test/pylint_test.py
test/storage_test.py
test/wrapper_deprecation_test.py
test/wrapper_test.py
abllib-1.4.3.dist-info/METADATA
abllib-1.4.3.dist-info/WHEEL
abllib-1.4.3.dist-info/top_level.txt
abllib-1.4.3.dist-info/RECORD
