Metadata-Version: 2.4
Name: abllib
Version: 1.4.3
Summary: Ableytners' general-purpose python library, usable across various projects.
Author-email: Ableytner <ableytner@gmx.at>
License-Expression: GPL-3.0
Project-URL: Repository, https://github.com/Ableytner/abllib
Project-URL: Issues, https://github.com/Ableytner/abllib/issues
Classifier: Development Status :: 4 - Beta
Classifier: Operating System :: OS Independent
Classifier: Programming Language :: Python
Classifier: Programming Language :: Python :: 3
Classifier: Programming Language :: Python :: 3.11
Classifier: Programming Language :: Python :: 3.12
Classifier: Programming Language :: Python :: 3.13
Classifier: Programming Language :: Python :: 3.14
Classifier: Programming Language :: Python :: 3 :: Only
Classifier: Topic :: Software Development :: Libraries :: Python Modules
Requires-Python: >=3.11
License-File: LICENSE
Requires-Dist: dill==0.4.0
Requires-Dist: numpy==2.3.3
Provides-Extra: all
Requires-Dist: levenshtein==0.27.1; extra == "all"
Requires-Dist: pykakasi==2.3.0; extra == "all"
Provides-Extra: dev
Requires-Dist: pylint==3.3.9; extra == "dev"
Requires-Dist: pytest==8.4.2; extra == "dev"
Requires-Dist: mypy==1.18.2; extra == "dev"
Requires-Dist: pre-commit==4.3.0; extra == "dev"
Dynamic: license-file
